pynacci.py
pynacci-1.1.0.dist-info/LICENSE
pynacci-1.1.0.dist-info/METADATA
pynacci-1.1.0.dist-info/WHEEL
pynacci-1.1.0.dist-info/top_level.txt
pynacci-1.1.0.dist-info/RECORD
