Metadata-Version: 2.1
Name: pynacci
Version: 1.1.0
Summary: Una librería para trabajar con la serie de Fibonacci
Author: Pablo Álvaro
Author-email: palvaroh2000@gmail.com
License: MIT
Keywords: fibonacci mathematics generator
Classifier: Programming Language :: Python :: 3
Classifier: License :: OSI Approved :: MIT License
Classifier: Operating System :: OS Independent
Requires-Python: >=3.6
License-File: LICENSE
